{
  "db_name": "PostgreSQL",
  "query": "\n    SELECT id, area, counter_part, delivery_start, delivery_end, price, quantity_mwh, trade_side, trade_type\n    FROM imbalance_trades",
  "describe": {
    "columns": [
      {
        "ordinal": 0,
        "name": "id",
        "type_info": "Int4"
      },
      {
        "ordinal": 1,
        "name": "area",
        "type_info": "Varchar"
      },
      {
        "ordinal": 2,
        "name": "counter_part",
        "type_info": "Varchar"
      },
      {
        "ordinal": 3,
        "name": "delivery_start",
        "type_info": "Timestamptz"
      },
      {
        "ordinal": 4,
        "name": "delivery_end",
        "type_info": "Timestamptz"
      },
      {
        "ordinal": 5,
        "name": "price",
        "type_info": "Numeric"
      },
      {
        "ordinal": 6,
        "name": "quantity_mwh",
        "type_info": "Numeric"
      },
      {
        "ordinal": 7,
        "name": "trade_side",
        "type_info": "Varchar"
      },
      {
        "ordinal": 8,
        "name": "trade_type",
        "type_info": "Varchar"
      }
    ],
    "parameters": {
      "Left": []
    },
    "nullable": [
      false,
      false,
      false,
      false,
      false,
      true,
      false,
      false,
      false
    ]
  },
  "hash": "2c371b52dc34ee61f988ff5a485720a8fa0c96f70277f3dba2adbdccb235eafb"
}
